hypergumbo_lang_extended1/__init__.py
hypergumbo_lang_extended1/ada.py
hypergumbo_lang_extended1/agda.py
hypergumbo_lang_extended1/apex.py
hypergumbo_lang_extended1/bibtex.py
hypergumbo_lang_extended1/bitbake.py
hypergumbo_lang_extended1/capnp.py
hypergumbo_lang_extended1/cobol.py
hypergumbo_lang_extended1/d_lang.py
hypergumbo_lang_extended1/fennel.py
hypergumbo_lang_extended1/fish.py
hypergumbo_lang_extended1/gdscript.py
hypergumbo_lang_extended1/gleam.py
hypergumbo_lang_extended1/hack.py
hypergumbo_lang_extended1/haxe.py
hypergumbo_lang_extended1/janet.py
hypergumbo_lang_extended1/jsonnet.py
hypergumbo_lang_extended1/kdl.py
hypergumbo_lang_extended1/lean.py
hypergumbo_lang_extended1/llvm_ir.py
hypergumbo_lang_extended1/luau.py
hypergumbo_lang_extended1/nim.py
hypergumbo_lang_extended1/odin.py
hypergumbo_lang_extended1/pascal.py
hypergumbo_lang_extended1/pony.py
hypergumbo_lang_extended1/prisma.py
hypergumbo_lang_extended1/smithy.py
hypergumbo_lang_extended1/solidity.py
hypergumbo_lang_extended1/sparql.py
hypergumbo_lang_extended1/tcl.py
hypergumbo_lang_extended1/twig.py
hypergumbo_lang_extended1/v_lang.py
hypergumbo_lang_extended1/verilog.py
hypergumbo_lang_extended1/vhdl.py
hypergumbo_lang_extended1/wolfram.py
hypergumbo_lang_extended1/zig.py
hypergumbo_lang_extended1-2.0.0.dist-info/METADATA
hypergumbo_lang_extended1-2.0.0.dist-info/WHEEL
hypergumbo_lang_extended1-2.0.0.dist-info/entry_points.txt
hypergumbo_lang_extended1-2.0.0.dist-info/RECORD
