Metadata-Version: 2.4
Name: hypergumbo-lang-extended1
Version: 2.0.0
Summary: Extended language analyzers (set 1) for hypergumbo
Author: Hypergumbo contributors
License: AGPL-3.0-or-later
Keywords: code-graph,language-support,static-analysis
Classifier: Development Status :: 3 - Alpha
Classifier: License :: OSI Approved :: GNU Affero General Public License v3 or later (AGPLv3+)
Classifier: Programming Language :: Python :: 3
Classifier: Programming Language :: Python :: 3 :: Only
Requires-Python: >=3.10
Requires-Dist: hypergumbo-core==2.0.0
Requires-Dist: tree-sitter-agda>=0.2.1
Requires-Dist: tree-sitter-llvm>=1.1
Requires-Dist: tree-sitter-odin>=1.0
Requires-Dist: tree-sitter-solidity>=0.0.1
Requires-Dist: tree-sitter-verilog>=1.0
Requires-Dist: tree-sitter-vhdl>=1.2
Requires-Dist: tree-sitter-zig>=0.0.1
